apqc-0.1.3.dist-info/METADATA
apqc-0.1.3.dist-info/WHEEL
apqc-0.1.3.dist-info/licenses/LICENSE
apqc/__init__.py
apqc/density_estimation.py
apqc/pqc.py
apqc/sample_data/__init__.py
apqc/sample_data/generate_toy_datasets.py
apqc/utils.py
apqc-0.1.3.dist-info/RECORD
