Metadata-Version: 2.1
Name: APQC
Version: 0.1.3
Summary: Based on Accelerated Probabilistic Quantum Clustering
Author-Email: Iraitz <iraitzm@gmail.com>
License: MIT
Project-URL: Homepage, https://github.com/IraitzM/APQC
Requires-Python: <3.12,>=3.8
Requires-Dist: networkx>=2.8
Requires-Dist: numba>=0.55.2
Requires-Dist: numpy>=1.22.2
Requires-Dist: tensorflow>=2.7.0
Requires-Dist: scipy>=1.8.0
Requires-Dist: scikit-learn>=1.0.2
Requires-Dist: pandas>=1.4.2
